IPTK/__init__.py
IPTK/Analysis/AnalysisFunction.py
IPTK/Analysis/AnalysisRecipies.py
IPTK/Analysis/__init__.py
IPTK/Classes/Annotator.py
IPTK/Classes/Database.py
IPTK/Classes/Experiment.py
IPTK/Classes/ExperimentSet.py
IPTK/Classes/Features.py
IPTK/Classes/GOEngine.py
IPTK/Classes/HLAChain.py
IPTK/Classes/HLAMolecules.py
IPTK/Classes/HLASet.py
IPTK/Classes/MzMLExperiment.py
IPTK/Classes/MzMLExperimentSet.py
IPTK/Classes/Peptide.py
IPTK/Classes/Proband.py
IPTK/Classes/Protein.py
IPTK/Classes/TandomSpectra.py
IPTK/Classes/Tissue.py
IPTK/Classes/Wrappers.py
IPTK/Classes/__init__.py
IPTK/Classes/DataFeeders/__init__.py
IPTK/Classes/DataFeeders/gene_ncbi_10090_prot_encoding.py
IPTK/Classes/DataFeeders/gene_ncbi_9606_prot_encoding.py
IPTK/IO/InFunctions.py
IPTK/IO/MEMEInterface.py
IPTK/IO/OutFunctions.py
IPTK/IO/__init__.py
IPTK/IO/Interfaces/AFND.py
IPTK/IO/Interfaces/BuildInDB.py
IPTK/IO/Interfaces/IEDB.py
IPTK/IO/Interfaces/__init__.py
IPTK/Utils/AcceleratedFunction.py
IPTK/Utils/DevFunctions.py
IPTK/Utils/Mapping.py
IPTK/Utils/Types.py
IPTK/Utils/UtilityFunction.py
IPTK/Utils/__init__.py
IPTK/Utils/config.py
IPTK/Visualization/__init__.py
IPTK/Visualization/vizTools.py
iptkl-0.6.24.dist-info/METADATA
iptkl-0.6.24.dist-info/WHEEL
iptkl-0.6.24.dist-info/top_level.txt
iptkl-0.6.24.dist-info/RECORD
