Metadata-Version: 2.1
Name: iptkl
Version: 0.6.24
Summary: IPTK is a library specialized in the analysis of HLA-peptidomes identified through an immunopeptidomics pipeline.
Home-page: https://github.com/ikmb/iptoolkit
Author: Hesham ElAbd
Author-email: h.elabd@ikmb.uni-kiel.de
Project-URL: Documentation, https://iptk.readthedocs.io/en/latest/
Project-URL: Funding, https://www.genes-environment-inflammation.de
Project-URL: Tutorials, https://github.com/ikmb/iptoolkit/tree/master/Tutorials
Project-URL: Tracker, https://github.com/ikmb/iptoolkit/issues
Keywords: HLA immunopeptidomics antigen-processing antigen-presentation computational-immunology interactive-data-analysis MHC
Classifier: Development Status :: 3 - Alpha
Classifier: Programming Language :: Python :: 3
Classifier: License :: OSI Approved :: MIT License
Classifier: Operating System :: OS Independent
Classifier: Topic :: Scientific/Engineering :: Medical Science Apps.
Classifier: Intended Audience :: Science/Research
Classifier: Typing :: Typed
Requires-Python: >=3.7
Requires-Dist: pandas
Requires-Dist: biopython
Requires-Dist: seaborn
Requires-Dist: matplotlib
Requires-Dist: plotly
Requires-Dist: mhcnames
Requires-Dist: pyteomics
Requires-Dist: h5py
Requires-Dist: logomaker
Requires-Dist: colour
Requires-Dist: lxml
Requires-Dist: nglview
Requires-Dist: sklearn
Requires-Dist: scipy
Requires-Dist: numba
Requires-Dist: pyopenms
Requires-Dist: bokeh
Requires-Dist: holoviews
Requires-Dist: tqdm
Requires-Dist: goatools
Requires-Dist: dash
